pyrandom2pm/__init__.py
pyrandom2pm/__main__.py
pyrandom2pm/pyrandom2pm.py
pyrandom2pm-0.1.5.dist-info/LICENSE
pyrandom2pm-0.1.5.dist-info/METADATA
pyrandom2pm-0.1.5.dist-info/WHEEL
pyrandom2pm-0.1.5.dist-info/top_level.txt
pyrandom2pm-0.1.5.dist-info/RECORD
