Metadata-Version: 2.1
Name: pyrandom2pm
Version: 0.1.5
Summary: Pyrandom2pm is a fun package to generate random results. This could be used for random number generation, using it answer your questions using 8-ball, and other unsure scenarios.
Author-email: Minjae Lee <ml6722@nyu.edu>, Joseph Lee <jtl9244@nyu.edu>, Yiwei Luo <yl7408@nyu.edu>, Brendan Tang <bjt312@nyu.edu>
License: GNU GENERAL PUBLIC LICENSE
Project-URL: Homepage, https://github.com/software-students-spring2024/3-python-package-exercise-se-2pm3
Project-URL: Repository, https://github.com/software-students-spring2024/3-python-package-exercise-se-2pm3.git
Project-URL: Bug Tracker, https://github.com/software-students-spring2024/3-python-package-exercise-se-2pm3/issues
Keywords: python,package,build,random
Classifier: Programming Language :: Python :: 3
Classifier: Intended Audience :: Education
Classifier: Operating System :: OS Independent
Requires-Python: >=3.9
License-File: LICENSE
Provides-Extra: dev
Requires-Dist: pytest ; extra == 'dev'
